{
    "key": "group_5cf0d98c86971",
    "title": "Test Results - MetaBox",
    "fields": [],
    "location": [
        [
            {
                "param": "post_type",
                "operator": "==",
                "value": "test_results"
            }
        ]
    ],
    "menu_order": 0,
    "position": "normal",
    "style": "seamless",
    "label_placement": "top",
    "instruction_placement": "label",
    "hide_on_screen": "",
    "active": 1,
    "description": "",
    "acfe_display_title": "",
    "acfe_autosync": [
        "php",
        "json"
    ],
    "acfe_permissions": "",
    "acfe_note": "",
    "acfe_meta": "",
    "modified": 1559288341
}